foxpuppet/__init__.py
foxpuppet/expected.py
foxpuppet/foxpuppet.py
foxpuppet/region.py
foxpuppet/windows/__init__.py
foxpuppet/windows/base.py
foxpuppet/windows/browser/__init__.py
foxpuppet/windows/browser/bookmarks/__init__.py
foxpuppet/windows/browser/bookmarks/bookmark.py
foxpuppet/windows/browser/navbar.py
foxpuppet/windows/browser/notifications/__init__.py
foxpuppet/windows/browser/notifications/addons.py
foxpuppet/windows/browser/notifications/base.py
foxpuppet/windows/browser/panel_ui/__init__.py
foxpuppet/windows/browser/panel_ui/panel_ui.py
foxpuppet/windows/browser/urlbar.py
foxpuppet/windows/browser/window.py
foxpuppet/windows/manager.py
foxpuppet-1.0.6.dist-info/LICENSE.txt
foxpuppet-1.0.6.dist-info/METADATA
foxpuppet-1.0.6.dist-info/WHEEL
foxpuppet-1.0.6.dist-info/RECORD
