Metadata-Version: 2.1
Name: foxpuppet
Version: 1.0.6
Summary: 
License: Mozilla Public License 2.0 (MPL 2.0)
Author: Benjamin Forehand Jr
Author-email: bforehand@mozilla.com
Requires-Python: >=3.12,<4.0
Classifier: License :: Other/Proprietary License
Classifier: Programming Language :: Python :: 3
Classifier: Programming Language :: Python :: 3.12
Classifier: Programming Language :: Python :: 3.13
Requires-Dist: selenium (>=4.29.0,<5.0.0)
